{"count":1904,"next":"http://councils.g0v.tw/api/councilors/?page=173","previous":"http://councils.g0v.tw/api/councilors/?page=171","results":[{"url":"http://councils.g0v.tw/api/councilors/1727/","each_terms":[{"url":"http://councils.g0v.tw/api/councilors_terms/2866/","election_year":"2014","name":"陳凱榮","gender":"男","party":"中國國民黨","title":"議員","constituency":1,"county":"新竹縣","district":"竹北市","in_office":true,"contact_details":[],"term_start":"2014-12-25","term_end":{"date":"2018-12-24"},"education":"中華大學科管系畢業","experience":"新竹縣竹北市民代表會第五、六、七屆代表\n國防部後備幹部訓練班第389期\n新竹縣竹北市體育會籃球、慢速壘球委員會主任委員\n新竹縣竹北市義警義消分隊顧問\n新竹縣竹北市後備憲兵荷松協會顧問\n新竹縣竹北市陳姓宗親會總幹事\n新竹縣竹北市博愛國中家長會副會長\n我愛竹北發展協會理事長","remark":null,"image":"http://www.hcc.gov.tw/2016hcc/upload/manager/speaker_201610041300127.jpg","links":[{"url":"http://www.hcc.gov.tw/2016hcc/member/member-detail.php?skid=43","note":"議會個人官網"},{"url":"https://www.facebook.com/p0910258258","note":"個人網站"}],"social_media":null,"platform":"一、 督促縣府積極推動台大醫院於竹北設立728床急重症醫院及醫學中心，大幅提升醫療品質與就醫的便利。\n二、 積極爭取竹北市東區高鐵消防分隊的設立，保障市民百姓生命財產安全。\n三、 為狗狗請命：興建狗狗運動公園，並就現有公園另闢可供狗狗活動的專屬空間，宣導溜狗繫牽繩，隨手撿便便，讓愛狗溜狗人可以開心、放心的與家裡狗狗親密互動。\n四、 積極爭取中山高竹北交流道沿環北路設置引道工程的早日完工，以紓解俗稱\"五路財神\"(五個路口)的縣政二路與光明六路之交通。\n五、 積極爭取各項經費補助，全力協助竹北西區成為\"精緻農業與觀光休閒\"的特色地區，督促縣府積極輔導農產品行銷，加強新月沙灘、鳳崎落日、天德堂登山步道、海岸原生林區等觀景設施，帶動西區休閒觀光，繁榮經濟。\n六、 設立最有效率的服務專線，全年無休，24小時專人接聽，服務最熱忱積極有效率，用實際行動來愛竹北！","param":{"bills_role_statistics":{"total":61,"priproposer":0,"sponsor":0,"cosponsor":61},"suggestions_years":{"count":303,"sum":5927488,"years":[{"count":111,"sum":1939413,"suggest_year":"2015","small_purchase":110},{"count":192,"sum":3988075,"suggest_year":"2016","small_purchase":187}]},"suggestions_associations":[{"count":72,"sum":1540450,"label":"社區發展協會"},{"count":13,"sum":285000,"label":"體育會"},{"count":17,"sum":185000,"label":"宗親會"},{"count":5,"sum":65000,"label":"婦女會"},{"count":4,"sum":60000,"label":"功德會"},{"count":8,"sum":45000,"label":"協進會"},{"count":5,"sum":40000,"label":"農會"},{"count":3,"sum":20000,"label":"公會"},{"count":2,"sum":15000,"label":"促進會"},{"count":1,"sum":10000,"label":"學會"},{"count":1,"sum":10000,"label":"研習會"},{"count":1,"sum":5000,"label":"聯盟"},{"count":0,"sum":0,"label":"商會"},{"count":0,"sum":0,"label":"婦聯會"},{"count":0,"sum":0,"label":"同心會"},{"count":0,"sum":0,"label":"早起會"},{"count":0,"sum":0,"label":"健身會"},{"count":0,"sum":0,"label":"商業會"},{"count":0,"sum":0,"label":"長青會"},{"count":0,"sum":0,"label":"民眾服務社"}],"suggestions_piles":[{"count":218,"tokens":"協會|學會|商會|公會|協進會|促進會|研習會|婦聯會|婦女會|體育會|同心會|農會|早起會|健身會|宗親會|功德會|商業會|長青會|民眾服務社|聯盟","sum":3045450,"label":"協會"},{"count":31,"tokens":"消防局|消防隊|分隊|中隊","sum":643260,"label":"消防局"},{"count":20,"tokens":"警察局|分局","sum":208245,"label":"警察局"},{"count":1,"tokens":"國中|國小","sum":97000,"label":"國中、國小"},{"count":6,"tokens":"辦公室|辦公處","sum":60000,"label":"辦公室"},{"count":4,"tokens":"廟|宮","sum":25000,"label":"廟"}],"bills_party_diversity":[{"party":"中國國民黨","ratio":0.7303370786516854},{"party":"無黨籍","ratio":0.14325842696629212},{"party":"勞動黨","ratio":0.06179775280898876},{"party":"民國黨","ratio":0.025280898876404494},{"party":"綠黨","ratio":0.025280898876404494},{"party":"民主進步黨","ratio":0.014044943820224719}]},"councilor":"d751cb64e0c54648ae5ed76463cf9575"}],"uid":"d751cb64e0c54648ae5ed76463cf9575","name":"陳凱榮","birth":null,"former_names":"","identifiers":["陳凱榮"]},{"url":"http://councils.g0v.tw/api/councilors/1308/","each_terms":[{"url":"http://councils.g0v.tw/api/councilors_terms/2234/","election_year":"2009","name":"林保光","gender":"","party":"中國國民黨","title":"議員","constituency":1,"county":"新竹縣","district":"竹北市","in_office":true,"contact_details":[{"type":"email","value":"a16006@hcc.gov.tw","label":"E-mail"}],"term_start":"2009-12-25","term_end":{"date":"2014-12-25"},"education":"六家國小\n六家國中\n萬能工專\n中國醫藥學 院\n嘉南藥理科技大學 〈藥學士〉","experience":"後備軍人幹部輔導員\n新竹商業會理事長聯誼會創會長\n新竹縣音樂文化促進會理事長\n新竹縣西藥商公會理事長\n新竹縣藥劑生公會理事長\n新竹縣藥劑師公會常務理事\n竹北市聯合巡守協會理事長\n竹東高中家長會會長\n新竹縣義消顧問竹北佛光會顧問。","remark":null,"image":"http://www.hcc.gov.tw/03councilor/photo/IMG_0348s.jpg","links":[{"url":"http://www.hcc.gov.tw/03councilor/view.asp?id=53","note":"議會個人官網"},{"url":"http://www.hcc.gov.tw/blog/style03/04list.asp?ald_id=53","note":"個人網站"}],"social_media":null,"platform":"督促續發老人年金與增加弱勢津貼。\n推動母語教學與安親才藝課輔學習。\n強化生物科技園區公共設施與招商。\n振興台大園區遷入、繁榮週邊設施。\n增進警民合作與治安、道路交通便利。\n提升社區學習、體育、文化、藝術建設。\n監督縣府預算計劃精實，提升效率運用。\n清廉問政，追求政黨和諧與廉能政府。\n杜絕政府貪污與防止公務員浪費公帑。\n推動尊親孝順道德倫理教育與活動。\n增加公辦托兒所、托老所與安養院。\n多設立便民機構與服務中心，推動公寓大廈集中式住宅社區之治安、安全、衛生防護。\n推動六家地區傳統市場增建。\n督促頭前溪改造工程計劃，做好城鄉休閒環境。\n重新歸劃各里社區區域，建立資源共享，促使居民情感交流。\n成立各里道路速報中心電話，立即通報修補道路坑洞。","param":{"bills_role_statistics":{"total":39,"priproposer":17,"sponsor":18,"cosponsor":21},"diversity":{"":0.01274648533207552,"中國國民黨":0.6760719362820795,"民主進步黨":0.028444994368601935,"勞動黨":0.03980668418902963,"無黨籍":0.24292989982821342},"bills_party_diversity":[{"party":"中國國民黨","ratio":0.7336244541484717},{"party":"無黨籍","ratio":0.2096069868995633},{"party":"勞動黨","ratio":0.021834061135371178},{"party":"","ratio":0.017467248908296942},{"party":"民主進步黨","ratio":0.017467248908296942}]},"councilor":"5e1afd36dd5f4bc7a1075a55f3460ebd"},{"url":"http://councils.g0v.tw/api/councilors_terms/2867/","election_year":"2014","name":"林保光","gender":"男","party":"中國國民黨","title":"議員","constituency":1,"county":"新竹縣","district":"竹北市","in_office":true,"contact_details":[],"term_start":"2014-12-25","term_end":{"date":"2018-12-24"},"education":"嘉南藥理科技大學、中國醫藥大學（ 藥學系）","experience":"廣州中醫藥大學碩士畢、廣州中醫藥大學博士候選人\n國家藥師高考及格、新竹縣藥師公會常務理事\n仁愛國中家長會前會長\n竹東高中家長會前會長\n新竹縣跆拳道主委\n新竹縣鐵人三項主委\n客庄文化策進會主委\n新竹扶輪社會員\n新竹縣議會第十六、十七屆議員","remark":null,"image":"http://www.hcc.gov.tw/2016hcc/upload/manager/speaker_201610041255440.jpg","links":[{"url":"http://www.hcc.gov.tw/2016hcc/member/member-detail.php?skid=42","note":"議會個人官網"},{"url":"https://www.facebook.com/profile.php?id=100001967655993","note":"個人網站"}],"social_media":null,"platform":"一、 推動六家地區傳統市場增建。\n二、 督促繼續發放老人年金、鄰長津貼、生育補助、免費中小學營養午餐等福利政策。\n三、 加強關懷照顧身心障礙及弱勢團體，重視婦幼安全。\n四、 督促頭前溪改造工程計劃，做好城鄉休閒環境。\n五、 促請盡速規劃六家高鐵區建構國際世貿展覽中心101。\n六、 重新規劃各里社區區域，建立資源共享，促使居民情感交流。\n七、 監督縣府警政，建立警局及社區巡守隊e世代數位攝影連線，以維護原居民及新都住民，居住的安全與品質。\n八、 成立各里道路速報中心電話，立即通報修補道路坑洞。\n九、 建構六家學習體系。爭取六家國中小學，成為交大附中小，結合交大客家學院，打造交大六家學習園區，並保障六家國中直升六家高中人數比例50%，以符合就近入學精神，造福本市學生。\n十、 爭取國際書展在竹北舉辦。竹北體育場享有交通地利之便，在此舉辦必能提升本縣讀書風氣，帶動地方文創產業發展。","param":{"bills_role_statistics":{"total":48,"priproposer":11,"sponsor":11,"cosponsor":37},"suggestions_years":{"count":309,"sum":5114584,"years":[{"count":145,"sum":1767060,"suggest_year":"2015","small_purchase":145},{"count":164,"sum":3347524,"suggest_year":"2016","small_purchase":162}]},"suggestions_associations":[{"count":87,"sum":874000,"label":"社區發展協會"},{"count":14,"sum":310000,"label":"體育會"},{"count":23,"sum":230000,"label":"宗親會"},{"count":8,"sum":115000,"label":"促進會"},{"count":6,"sum":100000,"label":"公會"},{"count":9,"sum":50000,"label":"協進會"},{"count":8,"sum":50000,"label":"農會"},{"count":2,"sum":20000,"label":"婦女會"},{"count":2,"sum":10000,"label":"商會"},{"count":1,"sum":10000,"label":"民眾服務社"},{"count":0,"sum":0,"label":"學會"},{"count":0,"sum":0,"label":"研習會"},{"count":0,"sum":0,"label":"婦聯會"},{"count":0,"sum":0,"label":"同心會"},{"count":0,"sum":0,"label":"早起會"},{"count":0,"sum":0,"label":"健身會"},{"count":0,"sum":0,"label":"功德會"},{"count":0,"sum":0,"label":"商業會"},{"count":0,"sum":0,"label":"長青會"},{"count":0,"sum":0,"label":"聯盟"}],"suggestions_piles":[{"count":258,"tokens":"協會|學會|商會|公會|協進會|促進會|研習會|婦聯會|婦女會|體育會|同心會|農會|早起會|健身會|宗親會|功德會|商業會|長青會|民眾服務社|聯盟","sum":3074000,"label":"協會"},{"count":7,"tokens":"廟|宮","sum":175000,"label":"廟"},{"count":7,"tokens":"警察局|分局","sum":45000,"label":"警察局"},{"count":4,"tokens":"消防局|消防隊|分隊|中隊","sum":30000,"label":"消防局"},{"count":1,"tokens":"辦公室|辦公處","sum":22000,"label":"辦公室"},{"count":0,"tokens":"國中|國小","sum":0,"label":"國中、國小"}],"bills_party_diversity":[{"party":"中國國民黨","ratio":0.7628458498023716},{"party":"無黨籍","ratio":0.13043478260869565},{"party":"勞動黨","ratio":0.05138339920948617},{"party":"綠黨","ratio":0.039525691699604744},{"party":"民國黨","ratio":0.007905138339920948},{"party":"民主進步黨","ratio":0.007905138339920948}]},"councilor":"5e1afd36dd5f4bc7a1075a55f3460ebd"}],"uid":"5e1afd36dd5f4bc7a1075a55f3460ebd","name":"林保光","birth":null,"former_names":"","identifiers":["林保光","林保光"]},{"url":"http://councils.g0v.tw/api/councilors/1324/","each_terms":[{"url":"http://councils.g0v.tw/api/councilors_terms/2873/","election_year":"2014","name":"林光榮","gender":"男","party":"中國國民黨","title":"議員","constituency":11,"county":"新竹縣","district":"平地原住民","in_office":true,"contact_details":[],"term_start":"2014-12-25","term_end":{"date":"2018-12-24"},"education":"國立台北商專畢業","experience":"新竹縣北埔鄉公所主計員\n新竹縣芎林鄉公所主計員\n新竹縣關西鎮公所主計主任\n新竹縣關西鎮公所財政課長\n新竹縣關西鎮公所主任秘書\n新竹縣竹北市戶政事務所主任\n新竹縣政府戶政課課長\n新竹縣原住民權益發展協會理事長\n新竹縣議會第十六、十七屆縣議員","remark":null,"image":"http://www.hcc.gov.tw/2016hcc/upload/manager/speaker_201610041338162.jpg","links":[{"url":"http://www.hcc.gov.tw/2016hcc/member/member-detail.php?skid=66","note":"議會個人官網"},{"url":"https://www.facebook.com/kuyingkalang","note":"個人網站"}],"social_media":null,"platform":"捍衛平地原住民族權利與福利先鋒，普及照顧平地原住民族，具體政見：\n一、 平地原住民族教育政策：持續加強推行原住民族語言教學工作，要求都會區國中小學校設置專職各族族語教師，廣開原住民族語言教學課程；編列體育或才藝人才培育獎金或培訓經費，藉以培育原住民體育或藝術人才。另外，強化原住民各項職業訓練專班，以增進原住民各項專才，以增進就業。\n二、 平地原住民就業經濟政策：督促政府落實原住民族工作權保障法，加強原住民就業媒合服務。扶植原住民各項產業，打造屬於新竹縣原住民族文化創意產業，以改善原住民經濟，提昇就業機會。\n三、 平地原住民社會福利政策：督促政府落實原住民福利政策，並協助原住民納入政府多元福利網絡，充分爭取原住民各項社會福利資源，如租屋補助、購屋、修繕、急難救助、婦幼福利及醫療等各項補助經費。\n四、 平地原住民文化傳承政策：為積極保護本縣原住民優良傳統文化，主張定期舉辦原住民族文化祭儀等文化活動，以期保存原住民族文化並向下紮根。要求於各鄉鎮市區域成立頭目組織，並增列相關預算，建立政府與各頭目或原住民社團之管道，以強化原住民族文化發展。\n五、 平地原住民族群和諧政策：保障縣內各住民共存共榮，族群融合，要求不分族群，資源平均，以縮短原漢生活差距，共創美好的新竹縣。\n六、原住民的任何事就是我的事，原住民的小事就是我的大事。","param":{"bills_role_statistics":{"total":141,"priproposer":28,"sponsor":28,"cosponsor":113},"suggestions_years":{"count":135,"sum":7141299,"years":[{"count":72,"sum":2866299,"suggest_year":"2015","small_purchase":68},{"count":63,"sum":4275000,"suggest_year":"2016","small_purchase":56}]},"suggestions_associations":[{"count":4,"sum":405000,"label":"聯盟"},{"count":4,"sum":280000,"label":"功德會"},{"count":9,"sum":158000,"label":"社區發展協會"},{"count":4,"sum":80000,"label":"農會"},{"count":3,"sum":40000,"label":"體育會"},{"count":2,"sum":30000,"label":"婦女會"},{"count":2,"sum":25000,"label":"宗親會"},{"count":2,"sum":20000,"label":"促進會"},{"count":2,"sum":15000,"label":"協進會"},{"count":1,"sum":10000,"label":"民眾服務社"},{"count":0,"sum":0,"label":"學會"},{"count":0,"sum":0,"label":"商會"},{"count":0,"sum":0,"label":"公會"},{"count":0,"sum":0,"label":"研習會"},{"count":0,"sum":0,"label":"婦聯會"},{"count":0,"sum":0,"label":"同心會"},{"count":0,"sum":0,"label":"早起會"},{"count":0,"sum":0,"label":"健身會"},{"count":0,"sum":0,"label":"商業會"},{"count":0,"sum":0,"label":"長青會"}],"suggestions_piles":[{"count":81,"tokens":"協會|學會|商會|公會|協進會|促進會|研習會|婦聯會|婦女會|體育會|同心會|農會|早起會|健身會|宗親會|功德會|商業會|長青會|民眾服務社|聯盟","sum":2938000,"label":"協會"},{"count":2,"tokens":"消防局|消防隊|分隊|中隊","sum":20000,"label":"消防局"},{"count":0,"tokens":"辦公室|辦公處","sum":0,"label":"辦公室"},{"count":0,"tokens":"廟|宮","sum":0,"label":"廟"},{"count":0,"tokens":"警察局|分局","sum":0,"label":"警察局"},{"count":0,"tokens":"國中|國小","sum":0,"label":"國中、國小"}],"bills_party_diversity":[{"party":"中國國民黨","ratio":0.8428571428571429},{"party":"無黨籍","ratio":0.05},{"party":"民主進步黨","ratio":0.041428571428571426},{"party":"勞動黨","ratio":0.025714285714285714},{"party":"民國黨","ratio":0.02},{"party":"綠黨","ratio":0.02}]},"councilor":"4ffe995b61354c24aee10180f5ff8c7c"},{"url":"http://councils.g0v.tw/api/councilors_terms/2250/","election_year":"2009","name":"林光榮","gender":"","party":"中國國民黨","title":"議員","constituency":11,"county":"新竹縣","district":"平地原住民","in_office":true,"contact_details":[{"type":"email","value":"a16036@hcc.gov.tw","label":"E-mail"}],"term_start":"2009-12-25","term_end":{"date":"2014-12-25"},"education":"國立台北商專畢業","experience":"曾任新竹縣北埔鄉公所主計員\n新竹縣芎林鄉公所主計員\n新竹縣關西鎮公所主計主任\n新竹縣關西鎮公所財政課長\n新竹縣關西鎮公所主任秘書\n新竹縣竹北市戶政事務所主任\n新竹縣政府戶政課課長\n新竹縣原住民權益發展協會理事長\n現任新竹縣議會第十六屆縣議員","remark":null,"image":"http://www.hcc.gov.tw/03councilor/photo/IMG_0284s.jpg","links":[{"url":"http://www.hcc.gov.tw/03councilor/view.asp?id=78","note":"議會個人官網"},{"url":"http://www.hcc.gov.tw/blog/style03/04list.asp?ald_id=78","note":"個人網站"}],"social_media":null,"platform":"平地原住民教育培訓政策：持續推行原住民族語言教學工作，要求都會區廣開原住民族語言教學課程，以期落實族語生活化。增辦原住民各項職業訓練專班，以增進原住民各項專才，提昇就業競爭力。\n平地原住民就業經濟政策：督促政府落實原住民族工作權保障法，加強原住民就業媒合服務。全力扶植原住民各項產業，引進各方理念，同時全面結合縣內觀光等各項產業，打造新竹縣原住民族文化創意產業，以改善原住民經濟，提昇就業機會。\n平地原住民社會福利政策：督促政府落實原住民福利政策，充份爭取原住民各項社會福利資源如：租屋補助、購屋、修繕、急難救助、婦幼福利等各項補助經費。\n平地原住民文化傳承政策：積極保護本縣原住民優良傳統文化，主張定期舉辦原住民族文化祭儀等活動，以期保存原住民族文化並向下紮根。同時持續催生本縣原住民行政處之成立，以求事權統一，強化本縣原住民族文化發展。\n平地原住民族群和諧政策：保障縣內各住民共存共榮，族群融合，縮短原漢生活差距，共創美好的新竹縣。\n原住民的任何事就是我的事，原住民的小事就是我的大事。","param":{"bills_role_statistics":{"total":123,"priproposer":23,"sponsor":24,"cosponsor":99},"diversity":{"":0.017361434500349566,"中國國民黨":0.8185153526665443,"民主進步黨":0.01429121303985707,"勞動黨":0.014480117272878948,"無黨籍":0.13535188252037178},"bills_party_diversity":[{"party":"中國國民黨","ratio":0.7771739130434783},{"party":"無黨籍","ratio":0.1539855072463768},{"party":"勞動黨","ratio":0.030797101449275364},{"party":"民主進步黨","ratio":0.019927536231884056},{"party":"","ratio":0.018115942028985508}]},"councilor":"4ffe995b61354c24aee10180f5ff8c7c"}],"uid":"4ffe995b61354c24aee10180f5ff8c7c","name":"林光榮","birth":null,"former_names":"","identifiers":["林光榮","林光榮"]},{"url":"http://councils.g0v.tw/api/councilors/1325/","each_terms":[{"url":"http://councils.g0v.tw/api/councilors_terms/2251/","election_year":"2009","name":"陳正順","gender":"","party":"中國國民黨","title":"議員","constituency":10,"county":"新竹縣","district":"北埔鄉、峨眉鄉","in_office":true,"contact_details":[{"type":"email","value":"a17036@hcc.gov.tw","label":"E-mail"}],"term_start":"2009-12-25","term_end":{"date":"2014-12-25"},"education":"光復高級中學畢","experience":"北埔鄉二屆鄉長\n中華大學企管系結業","remark":null,"image":"http://www.hcc.gov.tw/03councilor/photo/IMG_0386s.jpg","links":[{"url":"http://www.hcc.gov.tw/03councilor/view.asp?id=77","note":"議會個人官網"},{"url":"http://www.hcc.gov.tw/blog/style03/04list.asp?ald_id=77","note":"個人網站"}],"social_media":null,"platform":"市區的發展已受到瓶頸，要以八年從政的經驗，經營的策略，再進一步促進繁榮，創造商機。\n老馬識途，爭取上級政府補助，整頓市容，促使有一級古蹟，三級古蹟發揚光大，發展成文化城，十二寮，峨眉湖為觀光勝地。\n結合北埔峨眉農會，發展產業文化，打響膨風茶，擂茶柿餅，柑橘等特產，增進業者的福利，增加農民的收入。\n營造無污染的居住環境，維護居民身體健康，將欲新設立危害北埔，峨眉之垃圾掩埋場連根廢除，趕離本地區免除後患。\n協助政府推動農村再生計劃，建設農村，改善社區人民生環境，提高生活品質。\n爭取活動資源，推動社團活動，營造幸福，快樂，健康欣欣向榮蓬勃發展的榮景。","param":{"suggestions_years":{"count":1,"sum":99000,"years":[{"count":1,"sum":99000,"suggest_year":"2014","small_purchase":1}]},"diversity":{"":0.022610803324099725,"中國國民黨":0.7739944573551183,"民主進步黨":0.007479552091129409,"勞動黨":0.04195771403639663,"無黨籍":0.15395747319325612},"bills_role_statistics":{"total":57,"priproposer":0,"sponsor":1,"cosponsor":56},"suggestions_associations":[{"count":0,"sum":0,"label":"社區發展協會"},{"count":0,"sum":0,"label":"學會"},{"count":0,"sum":0,"label":"商會"},{"count":0,"sum":0,"label":"公會"},{"count":0,"sum":0,"label":"協進會"},{"count":0,"sum":0,"label":"促進會"},{"count":0,"sum":0,"label":"研習會"},{"count":0,"sum":0,"label":"婦聯會"},{"count":0,"sum":0,"label":"婦女會"},{"count":0,"sum":0,"label":"體育會"},{"count":0,"sum":0,"label":"同心會"},{"count":0,"sum":0,"label":"農會"},{"count":0,"sum":0,"label":"早起會"},{"count":0,"sum":0,"label":"健身會"},{"count":0,"sum":0,"label":"宗親會"},{"count":0,"sum":0,"label":"功德會"},{"count":0,"sum":0,"label":"商業會"},{"count":0,"sum":0,"label":"長青會"},{"count":0,"sum":0,"label":"民眾服務社"},{"count":0,"sum":0,"label":"聯盟"}],"bills_party_diversity":[{"party":"中國國民黨","ratio":0.7620396600566572},{"party":"無黨籍","ratio":0.1529745042492918},{"party":"勞動黨","ratio":0.042492917847025496},{"party":"","ratio":0.0226628895184136},{"party":"民主進步黨","ratio":0.019830028328611898}],"suggestions_piles":[{"count":1,"tokens":"警察局|分局","sum":99000,"label":"警察局"},{"count":0,"tokens":"協會|學會|商會|公會|協進會|促進會|研習會|婦聯會|婦女會|體育會|同心會|農會|早起會|健身會|宗親會|功德會|商業會|長青會|民眾服務社|聯盟","sum":0,"label":"協會"},{"count":0,"tokens":"辦公室|辦公處","sum":0,"label":"辦公室"},{"count":0,"tokens":"廟|宮","sum":0,"label":"廟"},{"count":0,"tokens":"消防局|消防隊|分隊|中隊","sum":0,"label":"消防局"},{"count":0,"tokens":"國中|國小","sum":0,"label":"國中、國小"}]},"councilor":"22059f7365324bc2ad4d19f3d001f93d"},{"url":"http://councils.g0v.tw/api/councilors_terms/2874/","election_year":"2014","name":"陳正順","gender":"男","party":"中國國民黨","title":"議員","constituency":10,"county":"新竹縣","district":"北埔鄉、峨眉鄉","in_office":true,"contact_details":[],"term_start":"2014-12-25","term_end":{"date":"2018-12-24"},"education":"高中畢業","experience":"新竹縣議會第十七屆議員\n新竹縣北埔鄉第十二、十三屆鄉長","remark":null,"image":"http://www.hcc.gov.tw/2016hcc/upload/manager/speaker_201610041337102.jpg","links":[{"url":"http://www.hcc.gov.tw/2016hcc/member/member-detail.php?skid=65","note":"議會個人官網"},{"url":null,"note":"個人網站"}],"social_media":null,"platform":"一、 為民喉舌。\n二、 為鄉親發聲。\n三、 服務不分藍綠，問政只問黑白。\n四、 全力做好鄉親、鄉公所、縣政府的溝通橋樑。","param":{"bills_role_statistics":{"total":48,"priproposer":1,"sponsor":1,"cosponsor":47},"suggestions_years":{"count":284,"sum":3669635,"years":[{"count":138,"sum":1550635,"suggest_year":"2015","small_purchase":138},{"count":146,"sum":2119000,"suggest_year":"2016","small_purchase":146}]},"suggestions_associations":[{"count":109,"sum":1430197,"label":"社區發展協會"},{"count":33,"sum":370000,"label":"農會"},{"count":21,"sum":235000,"label":"宗親會"},{"count":8,"sum":90000,"label":"協進會"},{"count":8,"sum":80000,"label":"促進會"},{"count":7,"sum":80000,"label":"婦女會"},{"count":5,"sum":60000,"label":"學會"},{"count":5,"sum":50000,"label":"聯盟"},{"count":3,"sum":30000,"label":"研習會"},{"count":2,"sum":15000,"label":"民眾服務社"},{"count":1,"sum":10000,"label":"體育會"},{"count":0,"sum":0,"label":"商會"},{"count":0,"sum":0,"label":"公會"},{"count":0,"sum":0,"label":"婦聯會"},{"count":0,"sum":0,"label":"同心會"},{"count":0,"sum":0,"label":"早起會"},{"count":0,"sum":0,"label":"健身會"},{"count":0,"sum":0,"label":"功德會"},{"count":0,"sum":0,"label":"商業會"},{"count":0,"sum":0,"label":"長青會"}],"suggestions_piles":[{"count":239,"tokens":"協會|學會|商會|公會|協進會|促進會|研習會|婦聯會|婦女會|體育會|同心會|農會|早起會|健身會|宗親會|功德會|商業會|長青會|民眾服務社|聯盟","sum":2885197,"label":"協會"},{"count":22,"tokens":"消防局|消防隊|分隊|中隊","sum":280094,"label":"消防局"},{"count":7,"tokens":"警察局|分局","sum":140000,"label":"警察局"},{"count":1,"tokens":"廟|宮","sum":10000,"label":"廟"},{"count":0,"tokens":"辦公室|辦公處","sum":0,"label":"辦公室"},{"count":0,"tokens":"國中|國小","sum":0,"label":"國中、國小"}],"bills_party_diversity":[{"party":"中國國民黨","ratio":0.8428571428571429},{"party":"無黨籍","ratio":0.12857142857142856},{"party":"民主進步黨","ratio":0.02142857142857143},{"party":"民國黨","ratio":0.007142857142857143}]},"councilor":"22059f7365324bc2ad4d19f3d001f93d"}],"uid":"22059f7365324bc2ad4d19f3d001f93d","name":"陳正順","birth":null,"former_names":"","identifiers":["陳正順"]},{"url":"http://councils.g0v.tw/api/councilors/1311/","each_terms":[{"url":"http://councils.g0v.tw/api/councilors_terms/2868/","election_year":"2014","name":"葉芬英","gender":"女","party":"民主進步黨","title":"議員","constituency":1,"county":"新竹縣","district":"竹北市","in_office":true,"contact_details":[],"term_start":"2014-12-25","term_end":{"date":"2018-12-24"},"education":"光復中學","experience":"新竹縣議會第十五、十六屆議員張木海助理。\n新竹縣議會第十七屆議員","remark":null,"image":"http://www.hcc.gov.tw/2016hcc/upload/manager/speaker_201610041253314.jpg","links":[{"url":"http://www.hcc.gov.tw/2016hcc/member/member-detail.php?skid=41","note":"議會個人官網"},{"url":"https://www.facebook.com/profile.php?id=100010611280218","note":"個人網站"}],"social_media":null,"platform":"一、 做專任議員，一人當選兩人服務，真心，用心，誠心誠意為民喉舌，替百姓跑腿，解決困難。\n二、 督促縣府編列老人年金，生育、營養午餐預算，並按時發放。\n三、 積極爭取竹北市東區，設立國中、國小學校，解決學生上學之問題。\n四、 竹北各社區大樓、學校重要道路口，全面裝設監視器，維護學生及居民之安全和治安工作。\n五、 強烈要求有關單位要做到路要平、燈要亮、水溝要通，公共場所保持清潔，雜草要整理，提高市民生活品質。\n六、 建請縣府在頭前溪畔，營造國家級的清水河濱公園，供市民運動休閒。\n七、 積極爭取新豐鄉通往新竹市武陵路之幹道工程，以利縣市民之交通。\n八、 發展竹北西區沿海漁產觀光事業。","param":{"bills_role_statistics":{"total":54,"priproposer":1,"sponsor":2,"cosponsor":52},"suggestions_years":{"count":178,"sum":5877474,"years":[{"count":103,"sum":2368474,"suggest_year":"2015","small_purchase":101},{"count":75,"sum":3509000,"suggest_year":"2016","small_purchase":70}]},"suggestions_associations":[{"count":50,"sum":1154251,"label":"社區發展協會"},{"count":27,"sum":585000,"label":"宗親會"},{"count":4,"sum":90000,"label":"協進會"},{"count":6,"sum":85000,"label":"聯盟"},{"count":3,"sum":60000,"label":"農會"},{"count":1,"sum":20000,"label":"研習會"},{"count":1,"sum":10000,"label":"學會"},{"count":0,"sum":0,"label":"商會"},{"count":0,"sum":0,"label":"公會"},{"count":0,"sum":0,"label":"促進會"},{"count":0,"sum":0,"label":"婦聯會"},{"count":0,"sum":0,"label":"婦女會"},{"count":0,"sum":0,"label":"體育會"},{"count":0,"sum":0,"label":"同心會"},{"count":0,"sum":0,"label":"早起會"},{"count":0,"sum":0,"label":"健身會"},{"count":0,"sum":0,"label":"功德會"},{"count":0,"sum":0,"label":"商業會"},{"count":0,"sum":0,"label":"長青會"},{"count":0,"sum":0,"label":"民眾服務社"}],"suggestions_piles":[{"count":128,"tokens":"協會|學會|商會|公會|協進會|促進會|研習會|婦聯會|婦女會|體育會|同心會|農會|早起會|健身會|宗親會|功德會|商業會|長青會|民眾服務社|聯盟","sum":2894251,"label":"協會"},{"count":6,"tokens":"辦公室|辦公處","sum":146030,"label":"辦公室"},{"count":6,"tokens":"消防局|消防隊|分隊|中隊","sum":145098,"label":"消防局"},{"count":0,"tokens":"廟|宮","sum":0,"label":"廟"},{"count":0,"tokens":"警察局|分局","sum":0,"label":"警察局"},{"count":0,"tokens":"國中|國小","sum":0,"label":"國中、國小"}],"bills_party_diversity":[{"party":"中國國民黨","ratio":0.49583333333333335},{"party":"民主進步黨","ratio":0.2916666666666667},{"party":"民國黨","ratio":0.08333333333333333},{"party":"無黨籍","ratio":0.07916666666666666},{"party":"勞動黨","ratio":0.025},{"party":"綠黨","ratio":0.025}]},"councilor":"32d277308ee1431ba4a7a11fef13282e"},{"url":"http://councils.g0v.tw/api/councilors_terms/2237/","election_year":"2009","name":"葉芬英","gender":"","party":"民主進步黨","title":"議員","constituency":1,"county":"新竹縣","district":"竹北市","in_office":true,"contact_details":[{"type":"email","value":"a17006@hcc.gov.tw","label":"E-mail"}],"term_start":"2009-12-25","term_end":{"date":"2014-12-25"},"education":"竹東大同國小\n竹東國中\n光復中學","experience":"張木海議員第15.16屆助理","remark":null,"image":"http://www.hcc.gov.tw/03councilor/photo/IMG_0373s.jpg","links":[{"url":"http://www.hcc.gov.tw/03councilor/view.asp?id=49","note":"議會個人官網"},{"url":"http://www.hcc.gov.tw/blog/style03/04list.asp?ald_id=49","note":"個人網站"}],"social_media":null,"platform":"督促縣府編列老人年金、生育、營養午餐預算，並按時發放。\n做專任議員，一人當選，兩人竭誠為市民服務。\n建請縣府在頭前溪畔，營造國家級的清水河濱公園，供市民運動休閒。\n強烈要求有關單位編列預算，在本市各重要路口裝設監視系統，加強治安工作。\n嚴格監督縣府，路要平、燈要亮、水溝要通、綠美化市容工程，提高市民生活品質。\n發展竹北市西區沿海漁產觀光。\n爭取經費開闢西區，軍方廢棄坑道，作為觀光步道。","param":{"bills_role_statistics":{"total":59,"priproposer":5,"sponsor":6,"cosponsor":53},"diversity":{"":0.03289629242010195,"中國國民黨":0.44889058849910785,"民主進步黨":0.21645835738113006,"勞動黨":0.040253268378421955,"無黨籍":0.2615014933212387},"bills_party_diversity":[{"party":"中國國民黨","ratio":0.49142857142857144},{"party":"無黨籍","ratio":0.2742857142857143},{"party":"民主進步黨","ratio":0.1742857142857143},{"party":"勞動黨","ratio":0.04},{"party":"","ratio":0.02}]},"councilor":"32d277308ee1431ba4a7a11fef13282e"}],"uid":"32d277308ee1431ba4a7a11fef13282e","name":"葉芬英","birth":null,"former_names":"","identifiers":["葉芬英"]},{"url":"http://councils.g0v.tw/api/councilors/1444/","each_terms":[{"url":"http://councils.g0v.tw/api/councilors_terms/2370/","election_year":"2009","name":"張錦煌","gender":"男","party":"民主進步黨","title":"","constituency":4,"county":"基隆市","district":"中山區","in_office":true,"contact_details":[{"type":"email","value":"15406@kmc.gov.tw","label":"電子信箱"},{"type":"voice","value":"(02) 2437-3710","label":"電話"},{"type":"fax","value":"(02) 2437-1780","label":"傳真"},{"type":"address","value":"基隆市復興路212巷6弄35-1號","label":"通訊處"}],"term_start":"2009-12-25","term_end":{"date":"2014-12-25"},"education":"．經國健康暨管理技術學院副學士","experience":"．二屆基隆市議員\n．基市觀光協會常務理事\n．基隆市觀護人協會理事\n．基隆市中山高中家長會長\n．宜蘭同鄉會理事長\n．基隆市立委王拓辦公室特別助理\n．前大基隆有線電視台總經理\n．陳水扁、李進勇等基隆市競選總部主任、執行總幹事\n．謝長廷、蘇貞昌正副總統基隆市競選總部副主任委員\n．早餐店負責人","remark":null,"image":"http://www.kmc.gov.tw/kmcii/images/councillor_014.gif","links":[{"url":"http://www.kmc.gov.tw/KMCII/coun_info_14.aspx","note":"議會個人官網"}],"social_media":null,"platform":"．嚴格審查市府預算，為民眾看緊荷包，杜絕貪瀆、浪費。繼續督促市府均衡發展區域建設，繁榮地方。\n．推動捷運延伸至基隆計劃，嘉惠就學、就業人口，疏解道路擁塞，提昇交通品質。\n．爭取環海輕軌運輸，都會雙軌營運，城市交通發達，便利民眾，吸引人潮，擴展旅遊價值。\n．實現港都風光計劃，全面行銷基隆，提昇觀光：基隆市現有資源如：海港、砲台、燈塔、山洞等開放、維護整修並設置周邊設施及方便交通，增加觀光競爭力。\n．促進市府都市更新計劃，推動基隆火車站廣場與中山區動線全面連結打造環港形象商圈。\n．建議中山區外木山腳踏車道與人行步道以環港線路延伸至仁愛區，增加市民遊憩、運動場所。\n．促請設立外木山環海風景區流動形象商圈，增加市民就業機會。\n．繼續推動本市中、小學學生免費營養午餐，減輕家長負擔。\n","param":{"suggestions_years":{"count":2,"sum":192000,"years":[{"count":2,"sum":192000,"suggest_year":"2014","small_purchase":2}]},"suggestions_associations":[{"count":0,"sum":0,"label":"社區發展協會"},{"count":0,"sum":0,"label":"學會"},{"count":0,"sum":0,"label":"商會"},{"count":0,"sum":0,"label":"公會"},{"count":0,"sum":0,"label":"協進會"},{"count":0,"sum":0,"label":"促進會"},{"count":0,"sum":0,"label":"研習會"},{"count":0,"sum":0,"label":"婦聯會"},{"count":0,"sum":0,"label":"婦女會"},{"count":0,"sum":0,"label":"體育會"},{"count":0,"sum":0,"label":"同心會"},{"count":0,"sum":0,"label":"農會"},{"count":0,"sum":0,"label":"早起會"},{"count":0,"sum":0,"label":"健身會"},{"count":0,"sum":0,"label":"宗親會"},{"count":0,"sum":0,"label":"功德會"},{"count":0,"sum":0,"label":"商業會"},{"count":0,"sum":0,"label":"長青會"},{"count":0,"sum":0,"label":"民眾服務社"},{"count":0,"sum":0,"label":"聯盟"}],"suggestions_piles":[{"count":2,"tokens":"國中|國小","sum":192000,"label":"國中、國小"},{"count":0,"tokens":"協會|學會|商會|公會|協進會|促進會|研習會|婦聯會|婦女會|體育會|同心會|農會|早起會|健身會|宗親會|功德會|商業會|長青會|民眾服務社|聯盟","sum":0,"label":"協會"},{"count":0,"tokens":"辦公室|辦公處","sum":0,"label":"辦公室"},{"count":0,"tokens":"廟|宮","sum":0,"label":"廟"},{"count":0,"tokens":"警察局|分局","sum":0,"label":"警察局"},{"count":0,"tokens":"消防局|消防隊|分隊|中隊","sum":0,"label":"消防局"}]},"councilor":"b2726f3fac3b460db2ac42660237db82"},{"url":"http://councils.g0v.tw/api/councilors_terms/2604/","election_year":"2014","name":"張錦煌","gender":"男","party":"民主進步黨","title":"議員","constituency":4,"county":"基隆市","district":"中山區","in_office":true,"contact_details":[{"type":"address","value":"基隆市復興路212巷6弄35-1號","label":"服務處"},{"type":"voice","value":"(02) 2437-3710","label":"連絡電話"},{"type":"fax","value":"(02) 2437-1780","label":"傳真號碼"}],"term_start":"2014-12-25","term_end":{"date":"2018-12-24"},"education":null,"experience":"","remark":null,"image":"http://www.kmc.gov.tw/images/website/others/km14.jpg","links":[{"url":"http://www.kmc.gov.tw/members/123-member14","note":"議會個人官網"}],"social_media":null,"platform":"","param":{"suggestions_years":{"count":6,"sum":3497667,"years":[{"count":4,"sum":3387667,"suggest_year":"2015","small_purchase":1},{"count":2,"sum":110000,"suggest_year":"2016","small_purchase":2}]},"bills_role_statistics":{"total":8,"priproposer":0,"sponsor":7,"cosponsor":1},"attendance_statistics":{"absent":0,"total":66},"suggestions_associations":[{"count":0,"sum":0,"label":"社區發展協會"},{"count":0,"sum":0,"label":"學會"},{"count":0,"sum":0,"label":"商會"},{"count":0,"sum":0,"label":"公會"},{"count":0,"sum":0,"label":"協進會"},{"count":0,"sum":0,"label":"促進會"},{"count":0,"sum":0,"label":"研習會"},{"count":0,"sum":0,"label":"婦聯會"},{"count":0,"sum":0,"label":"婦女會"},{"count":0,"sum":0,"label":"體育會"},{"count":0,"sum":0,"label":"同心會"},{"count":0,"sum":0,"label":"農會"},{"count":0,"sum":0,"label":"早起會"},{"count":0,"sum":0,"label":"健身會"},{"count":0,"sum":0,"label":"宗親會"},{"count":0,"sum":0,"label":"功德會"},{"count":0,"sum":0,"label":"商業會"},{"count":0,"sum":0,"label":"長青會"},{"count":0,"sum":0,"label":"民眾服務社"},{"count":0,"sum":0,"label":"聯盟"}],"bills_party_diversity":[{"party":"民主進步黨","ratio":0.589041095890411},{"party":"中國國民黨","ratio":0.1917808219178082},{"party":"親民黨","ratio":0.1232876712328767},{"party":"無黨籍","ratio":0.0821917808219178},{"party":"民國黨","ratio":0.0136986301369863}],"suggestions_piles":[{"count":5,"tokens":"國中|國小","sum":3397667,"label":"國中、國小"},{"count":1,"tokens":"警察局|分局","sum":100000,"label":"警察局"},{"count":1,"tokens":"辦公室|辦公處","sum":65000,"label":"辦公室"},{"count":0,"tokens":"協會|學會|商會|公會|協進會|促進會|研習會|婦聯會|婦女會|體育會|同心會|農會|早起會|健身會|宗親會|功德會|商業會|長青會|民眾服務社|聯盟","sum":0,"label":"協會"},{"count":0,"tokens":"廟|宮","sum":0,"label":"廟"},{"count":0,"tokens":"消防局|消防隊|分隊|中隊","sum":0,"label":"消防局"}]},"councilor":"b2726f3fac3b460db2ac42660237db82"}],"uid":"b2726f3fac3b460db2ac42660237db82","name":"張錦煌","birth":"1955-07-04","former_names":"","identifiers":["張錦煌"]},{"url":"http://councils.g0v.tw/api/councilors/1661/","each_terms":[{"url":"http://councils.g0v.tw/api/councilors_terms/2600/","election_year":"2014","name":"曾紀嚴","gender":"男","party":"中國國民黨","title":"議員","constituency":3,"county":"基隆市","district":"仁愛區","in_office":true,"contact_details":[{"type":"voice","value":"(02)2425-9001","label":"連絡電話"},{"type":"fax","value":"(02)2425-8994","label":"傳真號碼"}],"term_start":"2014-12-25","term_end":{"date":"2018-12-24"},"education":null,"experience":"","remark":null,"image":"http://www.kmc.gov.tw/images/website/others/km10.jpg","links":[{"url":"http://www.kmc.gov.tw/members/119-member10","note":"議會個人官網"}],"social_media":null,"platform":"","param":{"suggestions_years":{"count":2,"sum":564500,"years":[{"count":1,"sum":467500,"suggest_year":"2015","small_purchase":0},{"count":1,"sum":97000,"suggest_year":"2016","small_purchase":1}]},"bills_role_statistics":{"total":50,"priproposer":0,"sponsor":35,"cosponsor":15},"attendance_statistics":{"absent":0,"total":66},"suggestions_associations":[{"count":0,"sum":0,"label":"社區發展協會"},{"count":0,"sum":0,"label":"學會"},{"count":0,"sum":0,"label":"商會"},{"count":0,"sum":0,"label":"公會"},{"count":0,"sum":0,"label":"協進會"},{"count":0,"sum":0,"label":"促進會"},{"count":0,"sum":0,"label":"研習會"},{"count":0,"sum":0,"label":"婦聯會"},{"count":0,"sum":0,"label":"婦女會"},{"count":0,"sum":0,"label":"體育會"},{"count":0,"sum":0,"label":"同心會"},{"count":0,"sum":0,"label":"農會"},{"count":0,"sum":0,"label":"早起會"},{"count":0,"sum":0,"label":"健身會"},{"count":0,"sum":0,"label":"宗親會"},{"count":0,"sum":0,"label":"功德會"},{"count":0,"sum":0,"label":"商業會"},{"count":0,"sum":0,"label":"長青會"},{"count":0,"sum":0,"label":"民眾服務社"},{"count":0,"sum":0,"label":"聯盟"}],"bills_party_diversity":[{"party":"中國國民黨","ratio":0.665948275862069},{"party":"無黨籍","ratio":0.13793103448275862},{"party":"親民黨","ratio":0.09051724137931035},{"party":"民主進步黨","ratio":0.08620689655172414},{"party":"民國黨","ratio":0.01939655172413793}],"suggestions_piles":[{"count":1,"tokens":"國中|國小","sum":467500,"label":"國中、國小"},{"count":1,"tokens":"辦公室|辦公處","sum":97000,"label":"辦公室"},{"count":0,"tokens":"協會|學會|商會|公會|協進會|促進會|研習會|婦聯會|婦女會|體育會|同心會|農會|早起會|健身會|宗親會|功德會|商業會|長青會|民眾服務社|聯盟","sum":0,"label":"協會"},{"count":0,"tokens":"廟|宮","sum":0,"label":"廟"},{"count":0,"tokens":"警察局|分局","sum":0,"label":"警察局"},{"count":0,"tokens":"消防局|消防隊|分隊|中隊","sum":0,"label":"消防局"}]},"councilor":"92ffba0c78da4e5087ec1cd8fa195bc5"}],"uid":"92ffba0c78da4e5087ec1cd8fa195bc5","name":"曾紀嚴","birth":"1976-07-08","former_names":"","identifiers":["曾紀嚴","曽紀嚴"]},{"url":"http://councils.g0v.tw/api/councilors/1457/","each_terms":[{"url":"http://councils.g0v.tw/api/councilors_terms/2383/","election_year":"2009","name":"何淑萍","gender":"女","party":"中國國民黨","title":"","constituency":2,"county":"基隆市","district":"信義區","in_office":true,"contact_details":[{"type":"email","value":"15502@kmc.gov.tw","label":"電子信箱"},{"type":"voice","value":"(02) 2428-2826","label":"電話"},{"type":"fax","value":"(02) 2425-2723","label":"傳真"},{"type":"address","value":"基隆市信二路249號3樓","label":"通訊處"}],"term_start":"2009-12-25","term_end":{"date":"2014-12-25"},"education":"．崇右技術學院\n．國立台灣海洋大學航運管理研究所企管碩士","experience":"．基隆市第十五、十六屆市議員\n．國民黨十七、十八全黨代表\n．國民黨十八全中央委員\n．東信國小家長會長\n．基隆市康乃馨志工團團長\n．基隆市消防局婦宣隊\n．基隆市民防信義中隊中隊長\n．基隆青溪婦聯會副主委","remark":null,"image":"http://www.kmc.gov.tw/kmcii/images/councillor_08.gif","links":[{"url":"http://www.kmc.gov.tw/KMCII/coun_info_8.aspx","note":"議會個人官網"}],"social_media":null,"platform":"．因應國際港口推動國中、小雙語教學，規劃良好英語生活教學環境，提高學童外語能力。\n．督促天外天掩埋場復育，規劃結合民眾需求的休閒公園。\n．改善生活環境，營造觀光廊帶，促進產業發展，提升生活水平。\n．促請市府照顧弱勢、關懷兒童、保護婦女，營造安全生活環境。\n．推動市容整頓，加強公共建設，營造新基隆。\n","param":{"suggestions_years":{"count":1,"sum":593125,"years":[{"count":1,"sum":593125,"suggest_year":"2014","small_purchase":0}]},"suggestions_associations":[{"count":0,"sum":0,"label":"社區發展協會"},{"count":0,"sum":0,"label":"學會"},{"count":0,"sum":0,"label":"商會"},{"count":0,"sum":0,"label":"公會"},{"count":0,"sum":0,"label":"協進會"},{"count":0,"sum":0,"label":"促進會"},{"count":0,"sum":0,"label":"研習會"},{"count":0,"sum":0,"label":"婦聯會"},{"count":0,"sum":0,"label":"婦女會"},{"count":0,"sum":0,"label":"體育會"},{"count":0,"sum":0,"label":"同心會"},{"count":0,"sum":0,"label":"農會"},{"count":0,"sum":0,"label":"早起會"},{"count":0,"sum":0,"label":"健身會"},{"count":0,"sum":0,"label":"宗親會"},{"count":0,"sum":0,"label":"功德會"},{"count":0,"sum":0,"label":"商業會"},{"count":0,"sum":0,"label":"長青會"},{"count":0,"sum":0,"label":"民眾服務社"},{"count":0,"sum":0,"label":"聯盟"}],"suggestions_piles":[{"count":1,"tokens":"國中|國小","sum":593125,"label":"國中、國小"},{"count":0,"tokens":"協會|學會|商會|公會|協進會|促進會|研習會|婦聯會|婦女會|體育會|同心會|農會|早起會|健身會|宗親會|功德會|商業會|長青會|民眾服務社|聯盟","sum":0,"label":"協會"},{"count":0,"tokens":"辦公室|辦公處","sum":0,"label":"辦公室"},{"count":0,"tokens":"廟|宮","sum":0,"label":"廟"},{"count":0,"tokens":"警察局|分局","sum":0,"label":"警察局"},{"count":0,"tokens":"消防局|消防隊|分隊|中隊","sum":0,"label":"消防局"}]},"councilor":"c33f653aadbe425cae07e03760051fe3"},{"url":"http://councils.g0v.tw/api/councilors_terms/2596/","election_year":"2014","name":"何淑萍","gender":"女","party":"中國國民黨","title":"議員","constituency":2,"county":"基隆市","district":"信義區","in_office":true,"contact_details":[{"type":"address","value":"基隆市信二路249號3樓","label":"服務處"},{"type":"voice","value":"(02) 2421-6858","label":"連絡電話"},{"type":"fax","value":"(02) 2425-2723","label":"傳真號碼"}],"term_start":"2014-12-25","term_end":{"date":"2018-12-24"},"education":null,"experience":"","remark":null,"image":"http://www.kmc.gov.tw/images/website/others/km08.jpg","links":[{"url":"http://www.kmc.gov.tw/members/117-member8","note":"議會個人官網"}],"social_media":null,"platform":"","param":{"suggestions_years":{"count":6,"sum":2073000,"years":[{"count":3,"sum":1977000,"suggest_year":"2015","small_purchase":1},{"count":3,"sum":96000,"suggest_year":"2016","small_purchase":1}]},"bills_role_statistics":{"total":19,"priproposer":3,"sponsor":14,"cosponsor":5},"attendance_statistics":{"absent":0,"total":66},"suggestions_associations":[{"count":0,"sum":0,"label":"社區發展協會"},{"count":0,"sum":0,"label":"學會"},{"count":0,"sum":0,"label":"商會"},{"count":0,"sum":0,"label":"公會"},{"count":0,"sum":0,"label":"協進會"},{"count":0,"sum":0,"label":"促進會"},{"count":0,"sum":0,"label":"研習會"},{"count":0,"sum":0,"label":"婦聯會"},{"count":0,"sum":0,"label":"婦女會"},{"count":0,"sum":0,"label":"體育會"},{"count":0,"sum":0,"label":"同心會"},{"count":0,"sum":0,"label":"農會"},{"count":0,"sum":0,"label":"早起會"},{"count":0,"sum":0,"label":"健身會"},{"count":0,"sum":0,"label":"宗親會"},{"count":0,"sum":0,"label":"功德會"},{"count":0,"sum":0,"label":"商業會"},{"count":0,"sum":0,"label":"長青會"},{"count":0,"sum":0,"label":"民眾服務社"},{"count":0,"sum":0,"label":"聯盟"}],"bills_party_diversity":[{"party":"中國國民黨","ratio":0.6974789915966386},{"party":"無黨籍","ratio":0.13445378151260504},{"party":"親民黨","ratio":0.10504201680672269},{"party":"民主進步黨","ratio":0.046218487394957986},{"party":"民國黨","ratio":0.01680672268907563}],"suggestions_piles":[{"count":4,"tokens":"國中|國小","sum":1975000,"label":"國中、國小"},{"count":0,"tokens":"協會|學會|商會|公會|協進會|促進會|研習會|婦聯會|婦女會|體育會|同心會|農會|早起會|健身會|宗親會|功德會|商業會|長青會|民眾服務社|聯盟","sum":0,"label":"協會"},{"count":0,"tokens":"辦公室|辦公處","sum":0,"label":"辦公室"},{"count":0,"tokens":"廟|宮","sum":0,"label":"廟"},{"count":0,"tokens":"警察局|分局","sum":0,"label":"警察局"},{"count":0,"tokens":"消防局|消防隊|分隊|中隊","sum":0,"label":"消防局"}]},"councilor":"c33f653aadbe425cae07e03760051fe3"}],"uid":"c33f653aadbe425cae07e03760051fe3","name":"何淑萍","birth":"1971-07-26","former_names":"","identifiers":["何淑萍"]},{"url":"http://councils.g0v.tw/api/councilors/1458/","each_terms":[{"url":"http://councils.g0v.tw/api/councilors_terms/2597/","election_year":"2014","name":"陳東財","gender":"男","party":"民主進步黨","title":"議員","constituency":2,"county":"基隆市","district":"信義區","in_office":true,"contact_details":[{"type":"address","value":"基隆市信二路67號","label":"服務處"},{"type":"voice","value":"(02) 2425-8378","label":"連絡電話"},{"type":"fax","value":"(02) 2423-4031","label":"傳真號碼"}],"term_start":"2014-12-25","term_end":{"date":"2018-12-24"},"education":null,"experience":"","remark":null,"image":"http://www.kmc.gov.tw/images/website/others/km07.jpg","links":[{"url":"http://www.kmc.gov.tw/members/116-member7","note":"議會個人官網"}],"social_media":null,"platform":"","param":{"suggestions_years":{"count":6,"sum":482000,"years":[{"count":3,"sum":295000,"suggest_year":"2015","small_purchase":3},{"count":3,"sum":187000,"suggest_year":"2016","small_purchase":2}]},"bills_role_statistics":{"total":18,"priproposer":0,"sponsor":10,"cosponsor":8},"attendance_statistics":{"absent":0,"total":66},"suggestions_associations":[{"count":0,"sum":0,"label":"社區發展協會"},{"count":0,"sum":0,"label":"學會"},{"count":0,"sum":0,"label":"商會"},{"count":0,"sum":0,"label":"公會"},{"count":0,"sum":0,"label":"協進會"},{"count":0,"sum":0,"label":"促進會"},{"count":0,"sum":0,"label":"研習會"},{"count":0,"sum":0,"label":"婦聯會"},{"count":0,"sum":0,"label":"婦女會"},{"count":0,"sum":0,"label":"體育會"},{"count":0,"sum":0,"label":"同心會"},{"count":0,"sum":0,"label":"農會"},{"count":0,"sum":0,"label":"早起會"},{"count":0,"sum":0,"label":"健身會"},{"count":0,"sum":0,"label":"宗親會"},{"count":0,"sum":0,"label":"功德會"},{"count":0,"sum":0,"label":"商業會"},{"count":0,"sum":0,"label":"長青會"},{"count":0,"sum":0,"label":"民眾服務社"},{"count":0,"sum":0,"label":"聯盟"}],"bills_party_diversity":[{"party":"中國國民黨","ratio":0.4240506329113924},{"party":"民主進步黨","ratio":0.3987341772151899},{"party":"親民黨","ratio":0.08227848101265822},{"party":"無黨籍","ratio":0.08227848101265822},{"party":"民國黨","ratio":0.012658227848101266}],"suggestions_piles":[{"count":3,"tokens":"警察局|分局","sum":290000,"label":"警察局"},{"count":1,"tokens":"辦公室|辦公處","sum":99000,"label":"辦公室"},{"count":2,"tokens":"國中|國小","sum":96000,"label":"國中、國小"},{"count":0,"tokens":"協會|學會|商會|公會|協進會|促進會|研習會|婦聯會|婦女會|體育會|同心會|農會|早起會|健身會|宗親會|功德會|商業會|長青會|民眾服務社|聯盟","sum":0,"label":"協會"},{"count":0,"tokens":"廟|宮","sum":0,"label":"廟"},{"count":0,"tokens":"消防局|消防隊|分隊|中隊","sum":0,"label":"消防局"}]},"councilor":"d3960c7ed38a4ee99240bc705d9636c5"},{"url":"http://councils.g0v.tw/api/councilors_terms/2384/","election_year":"2009","name":"陳東財","gender":"男","party":"民主進步黨","title":"","constituency":2,"county":"基隆市","district":"信義區","in_office":true,"contact_details":[{"type":"email","value":"15506@kmc.gov.tw","label":"電子信箱"},{"type":"voice","value":"(02) 2425-8378","label":"電話"},{"type":"fax","value":"(02) 2423-4031","label":"傳真"},{"type":"address","value":"基隆市信二路67號","label":"通訊處"}],"term_start":"2009-12-25","term_end":{"date":"2014-12-25"},"education":"．基隆海事職業學校肄業","experience":"．基隆市議會第十四、十五、十六屆議員\n．基隆市信義區義民里第十四、十五屆里長\n．民主進步黨全國黨代表\n．基隆陳胡姚宗親會常務理事\n．基隆宜蘭同鄉會理事\n．基隆網球委員會主任委員\n．基隆技術摩托車協會主任委員\n．基隆義消總隊顧問\n．基隆義警、民防信義分隊顧問","remark":null,"image":"http://www.kmc.gov.tw/kmcii/images/councillor_07.gif","links":[{"url":"http://www.kmc.gov.tw/KMCII/coun_info_7.aspx","note":"議會個人官網"}],"social_media":null,"platform":"．爭取萬瑞快速道路銜接調和街拓寬工程、打通中正區、信義區聯外交通的瓶頸。(業已完工通車，自此深澳坑地區的車輛直通中山高、北二高)。\n．加強推動落實婦幼保護，弱勢族群、身心障礙者生活津貼補助、就業訓練等福利。\n．促請政府重視兒童、青少年就學教育問題。\n．爭取經費改善低窪易淹水地區路面及排水系統工程，以維市民免受淹水之苦。\n．促請自來水公司更換老舊給水幹管、改善馬達加壓設備，以利解決夏季各社區正常供水問題。\n．促請市警局於各巷、弄及社區附近加強維安巡邏，以維護市民生命財產之安全。\n．促請政府重視失業問題，加強辦理中、高年齡職業訓練，增進失業民眾學習多重就職技能，並協助重返職場，降低失業率。\n．積極爭取公有土地規劃為市民運動休閒公園，以提昇市民休閒生活品質。\n．積極尋覓適當公有土地闢建停車場，以利解決各社區停車空間不足之問題。\n．積極爭取經費加強道路交通整頓、市容綠美化工程，打造繁榮進步的新基隆。\n．全心全力監督市政，專心專職為民服務。\n","param":{"suggestions_years":{"count":6,"sum":5136458,"years":[{"count":6,"sum":5136458,"suggest_year":"2014","small_purchase":0}]},"suggestions_associations":[{"count":0,"sum":0,"label":"社區發展協會"},{"count":0,"sum":0,"label":"學會"},{"count":0,"sum":0,"label":"商會"},{"count":0,"sum":0,"label":"公會"},{"count":0,"sum":0,"label":"協進會"},{"count":0,"sum":0,"label":"促進會"},{"count":0,"sum":0,"label":"研習會"},{"count":0,"sum":0,"label":"婦聯會"},{"count":0,"sum":0,"label":"婦女會"},{"count":0,"sum":0,"label":"體育會"},{"count":0,"sum":0,"label":"同心會"},{"count":0,"sum":0,"label":"農會"},{"count":0,"sum":0,"label":"早起會"},{"count":0,"sum":0,"label":"健身會"},{"count":0,"sum":0,"label":"宗親會"},{"count":0,"sum":0,"label":"功德會"},{"count":0,"sum":0,"label":"商業會"},{"count":0,"sum":0,"label":"長青會"},{"count":0,"sum":0,"label":"民眾服務社"},{"count":0,"sum":0,"label":"聯盟"}],"suggestions_piles":[{"count":4,"tokens":"國中|國小","sum":2695458,"label":"國中、國小"},{"count":0,"tokens":"協會|學會|商會|公會|協進會|促進會|研習會|婦聯會|婦女會|體育會|同心會|農會|早起會|健身會|宗親會|功德會|商業會|長青會|民眾服務社|聯盟","sum":0,"label":"協會"},{"count":0,"tokens":"辦公室|辦公處","sum":0,"label":"辦公室"},{"count":0,"tokens":"廟|宮","sum":0,"label":"廟"},{"count":0,"tokens":"警察局|分局","sum":0,"label":"警察局"},{"count":0,"tokens":"消防局|消防隊|分隊|中隊","sum":0,"label":"消防局"}]},"councilor":"d3960c7ed38a4ee99240bc705d9636c5"}],"uid":"d3960c7ed38a4ee99240bc705d9636c5","name":"陳東財","birth":"1951-12-05","former_names":"","identifiers":["陳東財"]},{"url":"http://councils.g0v.tw/api/councilors/1459/","each_terms":[{"url":"http://councils.g0v.tw/api/councilors_terms/2598/","election_year":"2014","name":"張漢土","gender":"男","party":"中國國民黨","title":"議員","constituency":2,"county":"基隆市","district":"信義區","in_office":true,"contact_details":[{"type":"address","value":"基隆市東明路221之1號2樓","label":"服務處"},{"type":"voice","value":"(02) 2466-6504","label":"連絡電話"},{"type":"fax","value":"(02) 2468-3707","label":"傳真號碼"}],"term_start":"2014-12-25","term_end":{"date":"2018-12-24"},"education":null,"experience":"","remark":null,"image":"http://www.kmc.gov.tw/images/website/others/km06.jpg","links":[{"url":"http://www.kmc.gov.tw/members/115-member6","note":"議會個人官網"}],"social_media":null,"platform":"","param":{"suggestions_years":{"count":6,"sum":1773667,"years":[{"count":5,"sum":1378667,"suggest_year":"2015","small_purchase":3},{"count":1,"sum":395000,"suggest_year":"2016","small_purchase":0}]},"bills_role_statistics":{"total":40,"priproposer":3,"sponsor":30,"cosponsor":10},"attendance_statistics":{"absent":0,"total":66},"suggestions_associations":[{"count":0,"sum":0,"label":"社區發展協會"},{"count":0,"sum":0,"label":"學會"},{"count":0,"sum":0,"label":"商會"},{"count":0,"sum":0,"label":"公會"},{"count":0,"sum":0,"label":"協進會"},{"count":0,"sum":0,"label":"促進會"},{"count":0,"sum":0,"label":"研習會"},{"count":0,"sum":0,"label":"婦聯會"},{"count":0,"sum":0,"label":"婦女會"},{"count":0,"sum":0,"label":"體育會"},{"count":0,"sum":0,"label":"同心會"},{"count":0,"sum":0,"label":"農會"},{"count":0,"sum":0,"label":"早起會"},{"count":0,"sum":0,"label":"健身會"},{"count":0,"sum":0,"label":"宗親會"},{"count":0,"sum":0,"label":"功德會"},{"count":0,"sum":0,"label":"商業會"},{"count":0,"sum":0,"label":"長青會"},{"count":0,"sum":0,"label":"民眾服務社"},{"count":0,"sum":0,"label":"聯盟"}],"bills_party_diversity":[{"party":"中國國民黨","ratio":0.7107231920199502},{"party":"無黨籍","ratio":0.12718204488778054},{"party":"民主進步黨","ratio":0.08229426433915212},{"party":"親民黨","ratio":0.06483790523690773},{"party":"民國黨","ratio":0.014962593516209476}],"suggestions_piles":[{"count":5,"tokens":"國中|國小","sum":1678667,"label":"國中、國小"},{"count":0,"tokens":"協會|學會|商會|公會|協進會|促進會|研習會|婦聯會|婦女會|體育會|同心會|農會|早起會|健身會|宗親會|功德會|商業會|長青會|民眾服務社|聯盟","sum":0,"label":"協會"},{"count":0,"tokens":"辦公室|辦公處","sum":0,"label":"辦公室"},{"count":0,"tokens":"廟|宮","sum":0,"label":"廟"},{"count":0,"tokens":"警察局|分局","sum":0,"label":"警察局"},{"count":0,"tokens":"消防局|消防隊|分隊|中隊","sum":0,"label":"消防局"}]},"councilor":"a84d2b90a34d4e7390fdffe6a8149e19"},{"url":"http://councils.g0v.tw/api/councilors_terms/2385/","election_year":"2009","name":"張漢土","gender":"男","party":"中國國民黨","title":"","constituency":2,"county":"基隆市","district":"信義區","in_office":true,"contact_details":[{"type":"email","value":"15603@kmc.gov.tw","label":"電子信箱"},{"type":"voice","value":"(02) 2466-6505","label":"電話"},{"type":"fax","value":"(02) 2466-6504","label":"傳真"},{"type":"address","value":"基隆市培德路135號5樓","label":"通訊處"}],"term_start":"2009-12-25","term_end":{"date":"2014-12-25"},"education":"．基隆市私立培德高職畢業","experience":"．基隆市13、14、15、16屆市議員\n．基隆市淡江校友會會長\n．基隆市退伍軍人理事長\n．基隆市培德高職校友會會長\n．基隆市張廖簡宗親會副理事長\n．基隆市早健會理事長\n．基隆市國際長青獅子會理事長\n．基隆市商業總會理事\n．基隆市傢俱商業公會理事長","remark":null,"image":"http://www.kmc.gov.tw/kmcii/images/councillor_06.gif","links":[{"url":"http://www.kmc.gov.tw/KMCII/coun_info_6.aspx","note":"議會個人官網"}],"social_media":null,"platform":"．要求市政府將田寮河整治，恢復四十年前河水清澈，魚蝦蹦跳的情景。\n．要求市政府將已定案本市交通外環中環道路儘速完成解決本市交通瓶頸。\n．要求市政府積極向中央爭取儘速完成汐止捷運延伸至基隆以利基隆觀光產業經濟蓬勃發展。\n．要求政府中小學生四眼田雞比例降低強化教室照明設備。\n．要求政府封閉社區的路燈監視器公款得進入社區裝設。\n．全力爭取弱勢團體社會福利。\n．全力督促市政府早日興建完成多功能小巨蛋運動場。\n．積極建議市政府向內政部營建署反應放寬建築容積率。\n．積極建議中央政府就國有土地出租辦法不一國兩制。\n．全心全力為民服務。","param":{"suggestions_years":{"count":4,"sum":3327500,"years":[{"count":4,"sum":3327500,"suggest_year":"2014","small_purchase":1}]},"suggestions_associations":[{"count":0,"sum":0,"label":"社區發展協會"},{"count":0,"sum":0,"label":"學會"},{"count":0,"sum":0,"label":"商會"},{"count":0,"sum":0,"label":"公會"},{"count":0,"sum":0,"label":"協進會"},{"count":0,"sum":0,"label":"促進會"},{"count":0,"sum":0,"label":"研習會"},{"count":0,"sum":0,"label":"婦聯會"},{"count":0,"sum":0,"label":"婦女會"},{"count":0,"sum":0,"label":"體育會"},{"count":0,"sum":0,"label":"同心會"},{"count":0,"sum":0,"label":"農會"},{"count":0,"sum":0,"label":"早起會"},{"count":0,"sum":0,"label":"健身會"},{"count":0,"sum":0,"label":"宗親會"},{"count":0,"sum":0,"label":"功德會"},{"count":0,"sum":0,"label":"商業會"},{"count":0,"sum":0,"label":"長青會"},{"count":0,"sum":0,"label":"民眾服務社"},{"count":0,"sum":0,"label":"聯盟"}],"suggestions_piles":[{"count":1,"tokens":"國中|國小","sum":948000,"label":"國中、國小"},{"count":0,"tokens":"協會|學會|商會|公會|協進會|促進會|研習會|婦聯會|婦女會|體育會|同心會|農會|早起會|健身會|宗親會|功德會|商業會|長青會|民眾服務社|聯盟","sum":0,"label":"協會"},{"count":0,"tokens":"辦公室|辦公處","sum":0,"label":"辦公室"},{"count":0,"tokens":"廟|宮","sum":0,"label":"廟"},{"count":0,"tokens":"警察局|分局","sum":0,"label":"警察局"},{"count":0,"tokens":"消防局|消防隊|分隊|中隊","sum":0,"label":"消防局"}]},"councilor":"a84d2b90a34d4e7390fdffe6a8149e19"}],"uid":"a84d2b90a34d4e7390fdffe6a8149e19","name":"張漢土","birth":"1952-10-16","former_names":"","identifiers":["張漢土"]}]}